adapters/__init__.py
adapters/alpha_vantage_adapter.py
domain/__init__.py
domain/command_handler.py
domain/plot_data.py
domain/statistics.py
entrypoints/__init__.py
entrypoints/cli_entrypoint.py
helpers/__init__.py
helpers/logger.py
ports/__init__.py
ports/stock_data_provider.py
stock_hexagonal_app-0.2.2.dist-info/LICENSE
stock_hexagonal_app-0.2.2.dist-info/METADATA
stock_hexagonal_app-0.2.2.dist-info/WHEEL
stock_hexagonal_app-0.2.2.dist-info/entry_points.txt
stock_hexagonal_app-0.2.2.dist-info/top_level.txt
stock_hexagonal_app-0.2.2.dist-info/RECORD
