Metadata-Version: 2.1
Name: stock-hexagonal-app
Version: 0.2.2
Summary: Python tool for analyzing stock data build on hexagonal architecture.
Author-email: Jeremiasz Macura <jeremiaszmacura99@gmail.com>
License: Copyright 2024 Jeremiasz Macura
Project-URL: documentation, https://jeremiaszmacura.github.io/stock-hexagonal-app/
Project-URL: source, https://github.com/Jeremiaszmacura/stock-hexagonal-app
Keywords: analyze,stock,hexagonal architecture
Classifier: Programming Language :: Python :: 3
Classifier: License :: OSI Approved :: MIT License
Classifier: Operating System :: OS Independent
Requires-Python: >=3.11
License-File: LICENSE
Requires-Dist: typer ==0.12.1
Requires-Dist: numpy ==1.26.4
Requires-Dist: pandas ==2.2.1
Requires-Dist: matplotlib ==3.8.4
Requires-Dist: keyring ==25.1.0
Provides-Extra: docs
Requires-Dist: mkdocs ==1.5.3 ; extra == 'docs'
Provides-Extra: qa
Requires-Dist: pre-commit ==3.7.0 ; extra == 'qa'
Provides-Extra: upload
Requires-Dist: build ==1.2.1 ; extra == 'upload'
Requires-Dist: twine ==5.0.0 ; extra == 'upload'
